kishor/__init__.py
kishor/download.py
kishor_dl-0.2.dist-info/METADATA
kishor_dl-0.2.dist-info/WHEEL
kishor_dl-0.2.dist-info/entry_points.txt
kishor_dl-0.2.dist-info/top_level.txt
kishor_dl-0.2.dist-info/RECORD
